{
  "slug": "hibiki-nv",
  "label": "響ジャパニーズハーモニー",
  "category": "japanese-whisky",
  "latest_price_boxed": 15000,
  "latest_price_no_box": 11000,
  "latest_price_opened": 6000,
  "trend": "flat",
  "pct_6m": 0.0,
  "pct_12m": 7.1,
  "history": [
    {
      "month": "2025-06",
      "boxed": 14000,
      "no_box": 10000,
      "opened": 6000
    },
    {
      "month": "2025-07",
      "boxed": 15000,
      "no_box": 11000,
      "opened": 6000
    },
    {
      "month": "2025-08",
      "boxed": 15000,
      "no_box": 11000,
      "opened": 6000
    },
    {
      "month": "2025-09",
      "boxed": 15000,
      "no_box": 11000,
      "opened": 6000
    },
    {
      "month": "2025-10",
      "boxed": 15000,
      "no_box": 11000,
      "opened": 6000
    },
    {
      "month": "2025-11",
      "boxed": 15000,
      "no_box": 11000,
      "opened": 6000
    },
    {
      "month": "2025-12",
      "boxed": 14000,
      "no_box": 10000,
      "opened": 6000
    },
    {
      "month": "2026-01",
      "boxed": 15000,
      "no_box": 11000,
      "opened": 6000
    },
    {
      "month": "2026-02",
      "boxed": 15000,
      "no_box": 11000,
      "opened": 6000
    },
    {
      "month": "2026-03",
      "boxed": 15000,
      "no_box": 11000,
      "opened": 6000
    },
    {
      "month": "2026-04",
      "boxed": 15000,
      "no_box": 11000,
      "opened": 6000
    },
    {
      "month": "2026-05",
      "boxed": 15000,
      "no_box": 11000,
      "opened": 6000
    }
  ],
  "updated_at": "2026-05-17",
  "data_disclaimer": "本データは公開オークション情報・業者公開価格・市場ニュースを基にPeatBid編集部が独自に算出した推定相場です。実取引価格を保証するものではありません。",
  "data_sources": [
    "業者公開買取相場表（4社）",
    "公開オークション結果（国内・海外）",
    "市場ニュース・専門誌",
    "編集部独自調査"
  ]
}